[
  {
    "pillar": "colony-health",
    "slug": "hygienic-behaviour-testing",
    "title": "Hygienic behaviour testing",
    "summary": "Simple field tests to gauge how effectively a colony detects and removes unhealthy brood.",
    "level": "intermediate",
    "format": "article",
    "tags": ["hygiene", "behaviour", "testing", "health"],
    "updated": "2025-10-24",
    "url": "/wiki/colony-health/hygienic-behaviour-testing.html",
    "status": "published",
    "priority": 2,
    "indexable": true,
    "related": []
  },
  {
    "pillar": "colony-health",
    "slug": "queen-replacement-signs",
    "title": "Queen replacement signs",
    "summary": "How to recognise when a colony is preparing to replace its queen, and how to respond calmly and effectively.",
    "level": "intermediate",
    "format": "article",
    "tags": ["queens", "supersedure", "inspection", "health"],
    "updated": "2025-10-24",
    "url": "/wiki/colony-health/queen-replacement-signs.html",
    "status": "published",
    "priority": 2,
    "indexable": true,
    "related": []
  },
  {
    "pillar": "colony-health",
    "slug": "varroa-monitoring-schedule",
    "title": "Varroa monitoring schedule",
    "summary": "Season-by-season thresholds and methods to detect and respond early.",
    "level": "newcomer",
    "format": "article",
    "tags": ["varroa", "monitoring", "health"],
    "updated": "2025-10-24",
    "url": "/wiki/colony-health/varroa-monitoring-schedule.html",
    "status": "published",
    "priority": 2,
    "indexable": true,
    "related": []
  },
  {
    "pillar": "foundations",
    "slug": "bee-castes-and-lifecycle",
    "title": "Bee castes & lifecycle",
    "summary": "Workers, queens, drones, and the stages from egg to adult.",
    "level": "newcomer",
    "format": "article",
    "tags": ["biology", "lifecycle", "castes"],
    "updated": "2025-10-18",
    "url": "/wiki/foundations/bee-castes-and-lifecycle.html",
    "status": "published",
    "priority": 2,
    "indexable": true,
    "related": []
  },
  {
    "pillar": "foundations",
    "slug": "bee-communication",
    "title": "Bee communication",
    "summary": "How honeybees share information through dances, pheromones, and vibration — a social language evolved for survival.",
    "level": "intermediate",
    "format": "article",
    "tags": ["communication", "pheromones", "dance", "behaviour"],
    "updated": "2025-10-24",
    "url": "/wiki/foundations/bee-communication.html",
    "status": "published",
    "priority": 2,
    "indexable": true,
    "related": []
  },
  {
    "pillar": "foundations",
    "slug": "glossary-antenna",
    "title": "Antenna",
    "summary": "A paired sensory organ on a bee’s head used for smell, taste, touch, temperature, humidity, and vibration detection.",
    "level": "newcomer",
    "format": "glossary",
    "tags": ["glossary", "anatomy", "senses"],
    "updated": "2025-10-24",
    "url": "/wiki/foundations/glossary-antenna.html",
    "status": "published",
    "priority": 2,
    "indexable": true,
    "related": []
  },
  {
    "pillar": "foundations",
    "slug": "hive-tool-basics",
    "title": "Hive tool basics",
    "summary": "Types of hive tools, safe techniques for prying and separating frames, and common mistakes to avoid.",
    "level": "newcomer",
    "format": "article",
    "tags": ["tools", "handling", "hive-tool"],
    "updated": "2025-10-24",
    "url": "/wiki/foundations/hive-tool-basics.html",
    "status": "published",
    "priority": 2,
    "indexable": true,
    "related": []
  },
  {
    "pillar": "foundations",
    "slug": "hive-types-overview",
    "title": "Hive types overview",
    "summary": "An introduction to the main hive designs used in modern beekeeping, and how to choose one that fits your beekeeping style.",
    "level": "newcomer",
    "format": "article",
    "tags": ["hive", "equipment", "design", "setup"],
    "updated": "2025-10-24",
    "url": "/wiki/foundations/hive-types-overview.html",
    "status": "published",
    "priority": 2,
    "indexable": true,
    "related": []
  },
  {
    "pillar": "habitat",
    "slug": "planting-for-pollinators",
    "title": "Planting for pollinators",
    "summary": "Design a bee-friendly garden or landscape with continuous nectar and pollen from early spring to late autumn.",
    "level": "newcomer",
    "format": "article",
    "tags": ["habitat", "forage", "planting", "calendar"],
    "updated": "2025-10-24",
    "url": "/wiki/habitat/planting-for-pollinators.html",
    "status": "published",
    "priority": 2,
    "indexable": true,
    "related": []
  },
  {
    "pillar": "operations",
    "slug": "apiary-layout-basics",
    "title": "Apiary layout basics",
    "summary": "Positioning hives for safety, efficiency, and healthy bee flight lines in any setting.",
    "level": "newcomer",
    "format": "article",
    "tags": ["apiary", "layout", "site", "safety"],
    "updated": "2025-10-24",
    "url": "/wiki/operations/apiary-layout-basics.html",
    "status": "published",
    "priority": 2,
    "indexable": true,
    "related": []
  },
  {
    "pillar": "operations",
    "slug": "feeding-basics",
    "title": "Feeding basics",
    "summary": "When to feed, what to feed, and how to feed safely without triggering robbing or stressing the colony.",
    "level": "newcomer",
    "format": "article",
    "tags": ["feeding", "syrup", "fondant", "operations"],
    "updated": "2025-10-24",
    "url": "/wiki/operations/feeding-basics.html",
    "status": "published",
    "priority": 2,
    "indexable": true,
    "related": []
  },
  {
    "pillar": "operations",
    "slug": "first-inspection-checklist",
    "title": "First inspection checklist",
    "summary": "A calm, step-by-step checklist for safe, useful hive inspections: what to prepare, what to look for, and when to stop.",
    "level": "newcomer",
    "format": "article",
    "tags": ["inspection", "checklist", "records"],
    "updated": "2025-10-24",
    "url": "/wiki/operations/first-inspection-checklist.html",
    "status": "published",
    "priority": 2,
    "indexable": true,
    "related": []
  },
  {
    "pillar": "operations",
    "slug": "swarm-signs-and-prevention",
    "title": "Swarm signs & prevention",
    "summary": "Recognise early swarm signals and use simple, reliable actions to keep colonies productive and intact.",
    "level": "intermediate",
    "format": "article",
    "tags": ["swarm", "prevention", "split", "demaree"],
    "updated": "2025-10-24",
    "url": "/wiki/operations/swarm-signs-and-prevention.html",
    "status": "published",
    "priority": 2,
    "indexable": true,
    "related": []
  },
  {
    "pillar": "operations",
    "slug": "winter-prep-checklist",
    "title": "Winter prep checklist",
    "summary": "A practical, step-by-step checklist to prepare colonies for winter: stores, health, equipment, ventilation, and emergency plans.",
    "level": "newcomer",
    "format": "article",
    "tags": ["winter", "preparation", "feeding", "ventilation", "records"],
    "updated": "2025-10-24",
    "url": "/wiki/operations/winter-prep-checklist.html",
    "status": "published",
    "priority": 2,
    "indexable": true,
    "related": []
  },


  {
    "pillar": "operations",
    "slug": "honey-supering",
    "title": "Adding Supers (Supering)",
    "summary": "When and how to add honey supers to the hive to prevent swarming and increase yield.",
    "level": "intermediate",
    "format": "how-to",
    "tags": ["supering", "honey-harvest"],
    "updated": "2025-10-25",
    "url": "/wiki/operations/honey-supering.html",
    "status": "published",
    "priority": 1,
    "indexable": true,
    "related": []
  },
  {
    "pillar": "operations",
    "slug": "hive-swarming-prevention",
    "title": "Advanced Swarm Prevention",
    "summary": "Techniques beyond basic steps to further reduce swarm risk.",
    "level": "advanced",
    "format": "article",
    "tags": ["swarming", "prevention"],
    "updated": "2025-10-25",
    "url": "/wiki/operations/hive-swarming-prevention.html",
    "status": "published",
    "priority": 2,
    "indexable": true,
    "related": []
  },
  {
    "pillar": "community-policy",
    "slug": "apiary-data-reporting",
    "title": "API Data Reporting Requirements",
    "summary": "Reporting colony losses and health data to agriculture agencies.",
    "level": "newcomer",
    "format": "article",
    "tags": ["reporting", "surveillance"],
    "updated": "2025-10-25",
    "url": "/wiki/community-policy/apiary-data-reporting.html",
    "status": "published",
    "priority": 2,
    "indexable": true,
    "related": []
  },
  {
    "pillar": "foundations",
    "slug": "glossary-apiary",
    "title": "Apiary (Glos)",
    "summary": "Definition of apiary: a location where beehives are kept.",
    "level": "newcomer",
    "format": "glossary",
    "tags": ["glossary", "apiary"],
    "updated": "2025-10-25",
    "url": "/wiki/foundations/glossary-apiary.html",
    "status": "published",
    "priority": 1,
    "indexable": true,
    "related": []
  },
  {
    "pillar": "community-policy",
    "slug": "apiary-inspections",
    "title": "Government Apiary Inspections",
    "summary": "What to expect during government health inspections and compliance.",
    "level": "intermediate",
    "format": "article",
    "tags": ["regulations", "inspection"],
    "updated": "2025-10-25",
    "url": "/wiki/community-policy/apiary-inspections.html",
    "status": "published",
    "priority": 2,
    "indexable": true,
    "related": []
  },
  {
    "pillar": "data-sensing",
    "slug": "bee-farm-management-software",
    "title": "Apiary Management Software",
    "summary": "Software solutions for tracking colonies, production, and scheduling.",
    "level": "intermediate",
    "format": "article",
    "tags": ["software", "management"],
    "updated": "2025-10-25",
    "url": "/wiki/data-sensing/bee-farm-management-software.html",
    "status": "published",
    "priority": 1,
    "indexable": true,
    "related": []
  },
  {
    "pillar": "community-policy",
    "slug": "apiary-placement-ordinance",
    "title": "Apiary Placement Guidelines",
    "summary": "Recommended distances from property lines, roads, and footpaths.",
    "level": "newcomer",
    "format": "article",
    "tags": ["safety", "layout"],
    "updated": "2025-10-25",
    "url": "/wiki/community-policy/apiary-placement-ordinance.html",
    "status": "published",
    "priority": 1,
    "indexable": true,
    "related": []
  },
  {
    "pillar": "community-policy",
    "slug": "apiary-registration",
    "title": "Apiary Registration Requirements",
    "summary": "Why and how beekeepers register hives with authorities.",
    "level": "newcomer",
    "format": "article",
    "tags": ["policy", "registration"],
    "updated": "2025-10-25",
    "url": "/wiki/community-policy/apiary-registration.html",
    "status": "published",
    "priority": 1,
    "indexable": true,
    "related": []
  },
  {
    "pillar": "foundations",
    "slug": "apiology-basics",
    "title": "Apiology (Study of Honey Bees)",
    "summary": "Overview of the science and practice of beekeeping (apiology), including basic goals and concepts.",
    "level": "newcomer",
    "format": "article",
    "tags": ["beekeeping", "definition", "science"],
    "updated": "2025-10-25",
    "url": "/wiki/foundations/apiology-basics.html",
    "status": "published",
    "priority": 1,
    "indexable": true,
    "related": []
  },
  {
    "pillar": "foundations",
    "slug": "bee-anatomy-abdomen",
    "title": "Bee Anatomy: Abdomen and Digestive System",
    "summary": "Overview of the honey bee abdomen, including digestive tract and honey stomach (crop).",
    "level": "newcomer",
    "format": "article",
    "tags": ["anatomy", "digestion", "abdomen"],
    "updated": "2025-10-25",
    "url": "/wiki/foundations/bee-anatomy-abdomen.html",
    "status": "published",
    "priority": 1,
    "indexable": true,
    "related": []
  },
  {
    "pillar": "foundations",
    "slug": "bee-anatomy-head",
    "title": "Bee Anatomy: Head",
    "summary": "Detailed look at honey bee head structures (eyes, antennae, proboscis) and their functions.",
    "level": "newcomer",
    "format": "article",
    "tags": ["anatomy", "head", "senses"],
    "updated": "2025-10-25",
    "url": "/wiki/foundations/bee-anatomy-head.html",
    "status": "published",
    "priority": 1,
    "indexable": true,
    "related": []
  },
  {
    "pillar": "foundations",
    "slug": "glossary-pollen-brick",
    "title": "Bee Bread (Glos)",
    "summary": "Definition of bee bread: pollen mixed with nectar and enzymes used as larval food.",
    "level": "newcomer",
    "format": "glossary",
    "tags": ["glossary", "bee-bread"],
    "updated": "2025-10-25",
    "url": "/wiki/foundations/glossary-pollen-brick.html",
    "status": "published",
    "priority": 2,
    "indexable": true,
    "related": []
  },
  {
    "pillar": "data-sensing",
    "slug": "bee-counting-technologies",
    "title": "Bee Counting Technologies",
    "summary": "Devices and algorithms for counting bees entering and leaving the hive.",
    "level": "advanced",
    "format": "article",
    "tags": ["counting", "camera"],
    "updated": "2025-10-25",
    "url": "/wiki/data-sensing/bee-counting-technologies.html",
    "status": "published",
    "priority": 2,
    "indexable": true,
    "related": []
  },
  {
    "pillar": "foundations",
    "slug": "bee-grooming-behavior",
    "title": "Bee Grooming and Hygiene",
    "summary": "Self- and mutual grooming behaviors of bees to remove debris and mites.",
    "level": "intermediate",
    "format": "article",
    "tags": ["grooming", "behavior", "hygiene"],
    "updated": "2025-10-25",
    "url": "/wiki/foundations/bee-grooming-behavior.html",
    "status": "published",
    "priority": 2,
    "indexable": true,
    "related": []
  },
  {
    "pillar": "foundations",
    "slug": "bee-senses-magnetoreception",
    "title": "Bee Magnetoreception and Navigation",
    "summary": "Research on bees’ ability to sense magnetic fields and navigate, still an emerging science.",
    "level": "advanced",
    "format": "article",
    "tags": ["senses", "navigation", "magnetic-field"],
    "updated": "2025-10-25",
    "url": "/wiki/foundations/bee-senses-magnetoreception.html",
    "status": "published",
    "priority": 3,
    "indexable": true,
    "related": []
  },
  {
    "pillar": "foundations",
    "slug": "bee-senses-olfaction",
    "title": "Bee Smell: Olfactory Senses and Pheromones",
    "summary": "Bee olfaction and pheromone communication, including recognition of colony members and food sources.",
    "level": "newcomer",
    "format": "article",
    "tags": ["senses", "pheromones", "communication"],
    "updated": "2025-10-25",
    "url": "/wiki/foundations/bee-senses-olfaction.html",
    "status": "published",
    "priority": 1,
    "indexable": true,
    "related": []
  },
  {
    "pillar": "foundations",
    "slug": "bee-senses-taste",
    "title": "Bee Taste and Flavor Detection",
    "summary": "How honey bees taste nectar and other substances, importance of sugar detection in foraging.",
    "level": "intermediate",
    "format": "article",
    "tags": ["senses", "taste", "foraging"],
    "updated": "2025-10-25",
    "url": "/wiki/foundations/bee-senses-taste.html",
    "status": "published",
    "priority": 3,
    "indexable": true,
    "related": []
  },
  {
    "pillar": "community-policy",
    "slug": "ethics-and-responsibility",
    "title": "Beekeeper Ethics and Responsibility",
    "summary": "Best practices to be a responsible beekeeper in the community.",
    "level": "newcomer",
    "format": "article",
    "tags": ["ethics", "stewardship"],
    "updated": "2025-10-25",
    "url": "/wiki/community-policy/ethics-and-responsibility.html",
    "status": "published",
    "priority": 2,
    "indexable": true,
    "related": []
  },
  {
    "pillar": "community-policy",
    "slug": "beekeeping-associations",
    "title": "Beekeeping Associations and Clubs",
    "summary": "Role of local and national associations in education and support.",
    "level": "newcomer",
    "format": "article",
    "tags": ["community", "education"],
    "updated": "2025-10-25",
    "url": "/wiki/community-policy/beekeeping-associations.html",
    "status": "published",
    "priority": 1,
    "indexable": true,
    "related": []
  },
  {
    "pillar": "community-policy",
    "slug": "zoning-and-urban-laws",
    "title": "Beekeeping and Zoning Laws",
    "summary": "Land-use regulations affecting keeping hives in urban and rural areas.",
    "level": "intermediate",
    "format": "article",
    "tags": ["zoning", "urban"],
    "updated": "2025-10-25",
    "url": "/wiki/community-policy/zoning-and-urban-laws.html",
    "status": "published",
    "priority": 1,
    "indexable": true,
    "related": []
  },
  {
    "pillar": "sustainability-environment",
    "slug": "bees-in-agriculture",
    "title": "Role of Bees in Sustainable Agriculture",
    "summary": "How bees contribute to crop yields and sustainable farming practices.",
    "level": "newcomer",
    "format": "article",
    "tags": ["agriculture", "pollination"],
    "updated": "2025-10-25",
    "url": "/wiki/sustainability-environment/bees-in-agriculture.html",
    "status": "published",
    "priority": 1,
    "indexable": true,
    "related": []
  },
  {
    "pillar": "foundations",
    "slug": "bee-products-beeswax",
    "title": "Beeswax: Properties and Wax Production",
    "summary": "How bees make beeswax, the properties of wax, and its role in comb building.",
    "level": "newcomer",
    "format": "article",
    "tags": ["beeswax", "comb", "production"],
    "updated": "2025-10-25",
    "url": "/wiki/foundations/bee-products-beeswax.html",
    "status": "published",
    "priority": 1,
    "indexable": true,
    "related": []
  },
  {
    "pillar": "sustainability-environment",
    "slug": "biodiversity-enhancement",
    "title": "Enhancing Biodiversity in Farms",
    "summary": "Planting hedgerows, wildflowers, and maintaining habitats to boost biodiversity.",
    "level": "newcomer",
    "format": "article",
    "tags": ["biodiversity", "farm"],
    "updated": "2025-10-25",
    "url": "/wiki/sustainability-environment/biodiversity-enhancement.html",
    "status": "published",
    "priority": 2,
    "indexable": true,
    "related": []
  },
  {
    "pillar": "data-sensing",
    "slug": "blockchain-traceability",
    "title": "Blockchain for Honey Traceability",
    "summary": "Using blockchain to secure honey supply chain data.",
    "level": "advanced",
    "format": "article",
    "tags": ["blockchain", "traceability"],
    "updated": "2025-10-25",
    "url": "/wiki/data-sensing/blockchain-traceability.html",
    "status": "published",
    "priority": 3,
    "indexable": true,
    "related": []
  },
  {
    "pillar": "operations",
    "slug": "brood-nest-orientation",
    "title": "Brood Nest Orientation",
    "summary": "Placement of frames (brood vs honey storage) within the brood chamber.",
    "level": "newcomer",
    "format": "article",
    "tags": ["brood-nest", "orientation"],
    "updated": "2025-10-25",
    "url": "/wiki/operations/brood-nest-orientation.html",
    "status": "published",
    "priority": 2,
    "indexable": true,
    "related": []
  },
  {
    "pillar": "sustainability-environment",
    "slug": "carbon-footprint-honey",
    "title": "Carbon Footprint of Beekeeping",
    "summary": "Considering energy use and emissions in bee farm equipment and operations.",
    "level": "advanced",
    "format": "article",
    "tags": ["sustainability", "emissions"],
    "updated": "2025-10-25",
    "url": "/wiki/sustainability-environment/carbon-footprint-honey.html",
    "status": "published",
    "priority": 3,
    "indexable": true,
    "related": []
  },
  {
    "pillar": "colony-health",
    "slug": "chalkbrood-disease",
    "title": "Chalkbrood Disease",
    "summary": "Fungal brood disease (chalkbrood); symptoms and prevention.",
    "level": "intermediate",
    "format": "article",
    "tags": ["disease", "fungus"],
    "updated": "2025-10-25",
    "url": "/wiki/colony-health/chalkbrood-disease.html",
    "status": "published",
    "priority": 2,
    "indexable": true,
    "related": []
  },
  {
    "pillar": "sustainability-environment",
    "slug": "pollinator-citizen-science",
    "title": "Citizen Science for Pollinators",
    "summary": "Participating in community monitoring projects to help bee conservation.",
    "level": "intermediate",
    "format": "article",
    "tags": ["citizen-science", "monitoring"],
    "updated": "2025-10-25",
    "url": "/wiki/sustainability-environment/pollinator-citizen-science.html",
    "status": "published",
    "priority": 3,
    "indexable": true,
    "related": []
  },
  {
    "pillar": "sustainability-environment",
    "slug": "climate-change-impacts",
    "title": "Climate Change Impacts on Beekeeping",
    "summary": "How global warming affects nectar flows, bloom times, and overwinter survival.",
    "level": "intermediate",
    "format": "article",
    "tags": ["climate", "impacts"],
    "updated": "2025-10-25",
    "url": "/wiki/sustainability-environment/climate-change-impacts.html",
    "status": "published",
    "priority": 1,
    "indexable": true,
    "related": []
  },
  {
    "pillar": "sustainability-environment",
    "slug": "climate-adaptive-breeds",
    "title": "Climate-Adapted Bee Breeds",
    "summary": "Breeds suited for warmer or cooler climates.",
    "level": "advanced",
    "format": "article",
    "tags": ["breeding", "climate"],
    "updated": "2025-10-25",
    "url": "/wiki/sustainability-environment/climate-adaptive-breeds.html",
    "status": "published",
    "priority": 3,
    "indexable": true,
    "related": []
  },
  {
    "pillar": "colony-health",
    "slug": "colony-collapse-disorder",
    "title": "Colony Collapse Disorder (CCD)",
    "summary": "Discussion of CCD: symptoms and potential causes (multi-factorial).",
    "level": "advanced",
    "format": "article",
    "tags": ["health", "colony-collapse"],
    "updated": "2025-10-25",
    "url": "/wiki/colony-health/colony-collapse-disorder.html",
    "status": "published",
    "priority": 2,
    "indexable": true,
    "related": []
  },
  {
    "pillar": "colony-health",
    "slug": "colony-diagnostics-tests",
    "title": "Colony Diagnostic Tests",
    "summary": "Sampling and testing for foulbrood, nosema, and mites.",
    "level": "intermediate",
    "format": "how-to",
    "tags": ["diagnostics", "testing"],
    "updated": "2025-10-25",
    "url": "/wiki/colony-health/colony-diagnostics-tests.html",
    "status": "published",
    "priority": 1,
    "indexable": true,
    "related": []
  },
  {
    "pillar": "colony-health",
    "slug": "hive-health-assessment",
    "title": "Colony Health Assessment",
    "summary": "How to assess overall colony health via adult and brood inspections.",
    "level": "newcomer",
    "format": "article",
    "tags": ["inspection", "health"],
    "updated": "2025-10-25",
    "url": "/wiki/colony-health/hive-health-assessment.html",
    "status": "published",
    "priority": 1,
    "indexable": true,
    "related": []
  },
  {
    "pillar": "data-sensing",
    "slug": "data-logging-best-practices",
    "title": "Data Logging Best Practices",
    "summary": "Techniques for reliable sensor installation and data logging.",
    "level": "newcomer",
    "format": "article",
    "tags": ["sensors", "best-practices"],
    "updated": "2025-10-25",
    "url": "/wiki/data-sensing/data-logging-best-practices.html",
    "status": "published",
    "priority": 2,
    "indexable": true,
    "related": []
  },
  {
    "pillar": "data-sensing",
    "slug": "data-management-practices",
    "title": "Data Management for Beekeepers",
    "summary": "Best practices for collecting, storing, and sharing hive data.",
    "level": "intermediate",
    "format": "article",
    "tags": ["data", "management"],
    "updated": "2025-10-25",
    "url": "/wiki/data-sensing/data-management-practices.html",
    "status": "published",
    "priority": 2,
    "indexable": true,
    "related": []
  },
  {
    "pillar": "colony-health",
    "slug": "deformed-wing-virus",
    "title": "Deformed Wing Virus",
    "summary": "Virus often vectored by Varroa; symptoms and relation to mite levels.",
    "level": "intermediate",
    "format": "article",
    "tags": ["virus", "varroa"],
    "updated": "2025-10-25",
    "url": "/wiki/colony-health/deformed-wing-virus.html",
    "status": "published",
    "priority": 2,
    "indexable": true,
    "related": []
  },
  {
    "pillar": "habitat",
    "slug": "bee-friendly-garden-design",
    "title": "Designing a Bee-Friendly Garden",
    "summary": "Selecting plants, shelter, and water sources to attract and support bees.",
    "level": "newcomer",
    "format": "article",
    "tags": ["pollinators", "garden"],
    "updated": "2025-10-25",
    "url": "/wiki/habitat/bee-friendly-garden-design.html",
    "status": "published",
    "priority": 1,
    "indexable": true,
    "related": []
  },
  {
    "pillar": "habitat",
    "slug": "flower-strip-design",
    "title": "Designing Flower Strips",
    "summary": "Planting linear pollinator strips along fields or gardens for continuous bloom.",
    "level": "intermediate",
    "format": "how-to",
    "tags": ["flower-strip", "planting"],
    "updated": "2025-10-25",
    "url": "/wiki/habitat/flower-strip-design.html",
    "status": "published",
    "priority": 2,
    "indexable": true,
    "related": []
  },
  {
    "pillar": "colony-health",
    "slug": "drone-brood-removal",
    "title": "Drone Brood Removal as Mite Control",
    "summary": "Catching and removing drone brood to reduce Varroa population.",
    "level": "newcomer",
    "format": "how-to",
    "tags": ["varroa", "drone"],
    "updated": "2025-10-25",
    "url": "/wiki/colony-health/drone-brood-removal.html",
    "status": "published",
    "priority": 1,
    "indexable": true,
    "related": []
  },
  {
    "pillar": "data-sensing",
    "slug": "apiary-drones",
    "title": "Drones for Apiary Inspection",
    "summary": "Using drones (UAVs) for remote hive surveys and landscape monitoring.",
    "level": "advanced",
    "format": "article",
    "tags": ["drones", "surveillance"],
    "updated": "2025-10-25",
    "url": "/wiki/data-sensing/apiary-drones.html",
    "status": "published",
    "priority": 3,
    "indexable": true,
    "related": []
  },
  {
    "pillar": "sustainability-environment",
    "slug": "sustainable-apiaries",
    "title": "Eco-Friendly Apiaries",
    "summary": "Practices like using solar wax melters and reusing materials.",
    "level": "intermediate",
    "format": "article",
    "tags": ["sustainability", "eco-friendly"],
    "updated": "2025-10-25",
    "url": "/wiki/sustainability-environment/sustainable-apiaries.html",
    "status": "published",
    "priority": 2,
    "indexable": true,
    "related": []
  },
  {
    "pillar": "community-policy",
    "slug": "emergency-response-plans",
    "title": "Emergency Response Plans",
    "summary": "Preparing for disasters (fires, floods) affecting apiaries.",
    "level": "intermediate",
    "format": "article",
    "tags": ["emergency", "preparedness"],
    "updated": "2025-10-25",
    "url": "/wiki/community-policy/emergency-response-plans.html",
    "status": "published",
    "priority": 2,
    "indexable": true,
    "related": []
  },
  {
    "pillar": "colony-health",
    "slug": "european-foulbrood",
    "title": "European Foulbrood Disease",
    "summary": "Bacterial disease of brood; causes, identification, and treatment.",
    "level": "newcomer",
    "format": "article",
    "tags": ["disease", "bacteria"],
    "updated": "2025-10-25",
    "url": "/wiki/colony-health/european-foulbrood.html",
    "status": "published",
    "priority": 1,
    "indexable": true,
    "related": []
  },
  {
    "pillar": "community-policy",
    "slug": "beekeeping-fair-trade",
    "title": "Fair Trade and Honey",
    "summary": "Fair trade programs that support ethical honey production.",
    "level": "advanced",
    "format": "article",
    "tags": ["fair-trade", "market"],
    "updated": "2025-10-25",
    "url": "/wiki/community-policy/beekeeping-fair-trade.html",
    "status": "published",
    "priority": 3,
    "indexable": true,
    "related": []
  },
  {
    "pillar": "operations",
    "slug": "feeding-fondant",
    "title": "Feeding Candy or Fondant in Winter",
    "summary": "Using sugar candy or fondant to feed bees in cold weather when syrup is not feasible.",
    "level": "intermediate",
    "format": "how-to",
    "tags": ["feeding", "fondant"],
    "updated": "2025-10-25",
    "url": "/wiki/operations/feeding-fondant.html",
    "status": "published",
    "priority": 2,
    "indexable": true,
    "related": []
  },
  {
    "pillar": "operations",
    "slug": "feeding-pollen-supplements",
    "title": "Feeding Pollen Supplements",
    "summary": "How and why to provide pollen substitute or patty to a colony.",
    "level": "newcomer",
    "format": "how-to",
    "tags": ["feeding", "pollen"],
    "updated": "2025-10-25",
    "url": "/wiki/operations/feeding-pollen-supplements.html",
    "status": "published",
    "priority": 2,
    "indexable": true,
    "related": []
  },
  {
    "pillar": "operations",
    "slug": "feeding-sugar-syrup",
    "title": "Feeding Sugar Syrup to Bees",
    "summary": "Mixing and applying sugar syrup for feeding bees in spring or winter.",
    "level": "newcomer",
    "format": "how-to",
    "tags": ["feeding", "sugar-syrup"],
    "updated": "2025-10-25",
    "url": "/wiki/operations/feeding-sugar-syrup.html",
    "status": "published",
    "priority": 1,
    "indexable": true,
    "related": []
  },
  {
    "pillar": "sustainability-environment",
    "slug": "forest-beekeeping-conservation",
    "title": "Forest Beekeeping and Conservation",
    "summary": "Maintaining bees in forested areas and planting for pollinators in woodlands.",
    "level": "intermediate",
    "format": "article",
    "tags": ["forest", "conservation"],
    "updated": "2025-10-25",
    "url": "/wiki/sustainability-environment/forest-beekeeping-conservation.html",
    "status": "published",
    "priority": 2,
    "indexable": true,
    "related": []
  },
  {
    "pillar": "data-sensing",
    "slug": "geospatial-bee-mapping",
    "title": "Geospatial Mapping of Apiaries",
    "summary": "Using GIS to plan apiary placement and forage mapping.",
    "level": "advanced",
    "format": "article",
    "tags": ["GIS", "mapping"],
    "updated": "2025-10-25",
    "url": "/wiki/data-sensing/geospatial-bee-mapping.html",
    "status": "published",
    "priority": 2,
    "indexable": true,
    "related": []
  },
  {
    "pillar": "sustainability-environment",
    "slug": "energy-saving-hive",
    "title": "Insulation and Hive Efficiency",
    "summary": "Insulating hives to reduce heating needs and increase overwintering success.",
    "level": "intermediate",
    "format": "article",
    "tags": ["insulation", "winter"],
    "updated": "2025-10-25",
    "url": "/wiki/sustainability-environment/energy-saving-hive.html",
    "status": "published",
    "priority": 2,
    "indexable": true,
    "related": []
  }
]
